random_image_from_folder/__init__.py
random_image_from_folder/templatetags/__init__.py
random_image_from_folder/templatetags/random_image.py
django_random_image_from_folder-0.0.3.dist-info/LICENSE
django_random_image_from_folder-0.0.3.dist-info/METADATA
django_random_image_from_folder-0.0.3.dist-info/WHEEL
django_random_image_from_folder-0.0.3.dist-info/top_level.txt
django_random_image_from_folder-0.0.3.dist-info/RECORD
