Metadata-Version: 2.1
Name: django-random-image-from-folder
Version: 0.0.3
Summary: Django Random Image From Folder is a simple app to load a random image from a specified directory.
Home-page: https://github.com/IlyaBat9/django-random-image-from-folder
Author: Ilya_Bat9
Author-email: nasirov@olympus.ru
License: UNKNOWN
Platform: UNKNOWN
Classifier: Programming Language :: Python :: 3
Classifier: License :: OSI Approved :: MIT License
Classifier: Operating System :: OS Independent
Classifier: Framework :: Django
